[{"type":"Point","coordinates":[13.2238898826158,8.53884345436462],"properties":{"name":"Stone Mill","type":"Landmark","id":113}},{"type":"Point","coordinates":[9.17771407866206,8.7631118592027],"properties":{"name":"Pendric Hills","type":"Landmark","id":219}},{"type":"Point","coordinates":[6.61660075431014,12.1306952451513],"properties":{"name":"Nagga's Bones","type":"Landmark","id":223}},{"type":"Point","coordinates":[16.2421688310617,37.2124934646006],"properties":{"name":"Fist of the First Men","type":"Landmark","id":216}},{"type":"Point","coordinates":[13.4061079615468,6.52042781082185],"properties":{"name":"Hollow Hill","type":"Landmark","id":233}},{"type":"Point","coordinates":[20.3981427082175,5.04165801642078],"properties":{"name":"Old Stone Bridge Inn","type":"Landmark","id":48}},{"type":"Point","coordinates":[24.7223178890018,-8.72047920129964],"properties":{"name":"Water Gardens","type":"Landmark","id":114}},{"type":"Point","coordinates":[9.8131412257033,9.50132869179472],"properties":{"name":"Nunn's Deep","type":"Landmark","id":220}},{"type":"Point","coordinates":[14.6489287050245,6.84748590121074],"properties":{"name":"Tumblers Falls","type":"Landmark","id":232}},{"type":"Point","coordinates":[16.3963533593879,7.9221053410599],"properties":{"name":"Rushing Falls","type":"Landmark","id":231}},{"type":"Point","coordinates":[12.7426472639008,7.23995560967737],"properties":{"name":"Mummer's Ford","type":"Landmark","id":235}},{"type":"Point","coordinates":[14.8731971098626,10.2769235918598],"properties":{"name":"Inn of the Kneeling Man","type":"Landmark","id":243}},{"type":"Point","coordinates":[40.7262438872913,0.859853062712471],"properties":{"name":"Dagger Lake","type":"Landmark","id":292}},{"type":"Point","coordinates":[17.0632297229854,7.38758110803825],"properties":{"name":"God's Eye","type":"Landmark","id":293}},{"type":"Point","coordinates":[17.3080195246851,29.7450496632791],"properties":{"name":"Long Lake","type":"Landmark","id":294}},{"type":"Point","coordinates":[17.3401495630815,9.81904226531535],"properties":{"name":"Crossroads Inn","type":"Landmark","id":226}}]